{
  "MBCCSH05": {
    "high": "100.00000000",
    "low": "100.00000000",
    "vol": "527.5",
    "last": "100.00000000",
    "buy": "0",
    "sell": "100",
    "open": "100.00000000",
    "date": 1663613124
  },
  "MBCCSH06": {
    "high": "100.00000000",
    "low": "100.00000000",
    "vol": "51",
    "last": "100.00000000",
    "buy": "0",
    "sell": "100",
    "open": "100.00000000",
    "date": 1663605276
  },
  "MBPRK06": {
    "high": "119.81000000",
    "low": "114.80000000",
    "vol": "76.65309488",
    "last": "119.81000000",
    "buy": "114.87001",
    "sell": "119.79999",
    "open": "114.81000000",
    "date": 1663630336
  },
  "MBPRK07": {
    "high": "119.98000000",
    "low": "115.88000000",
    "vol": "64.84094757",
    "last": "119.98000000",
    "buy": "111.14",
    "sell": "115.88",
    "open": "116.00000000",
    "date": 1663632326
  }
}
